libjdrones/_core.cpython-311-x86_64-linux-musl.so
libjdrones/_version.py
libjdrones/__init__.py
libjdrones-0.1.1.dist-info/RECORD
libjdrones-0.1.1.dist-info/WHEEL
libjdrones-0.1.1.dist-info/METADATA
libjdrones-0.1.1.dist-info/licenses/LICENSE.txt
libjdrones.libs/libjdrones-5c24f316.so
libjdrones.libs/libstdc++-a9383cce.so.6.0.28
libjdrones.libs/libgcc_s-a04fdf82.so.1
