Metadata-Version: 2.1
Name: libjdrones
Version: 0.1.1
Summary: A C++ library to speed up jdrones computations
License:                     GNU GENERAL PUBLIC LICENSE
Classifier: Development Status :: 3 - Alpha
Classifier: Natural Language :: English
Classifier: Operating System :: Unix
Classifier: Topic :: Scientific/Engineering
Classifier: Topic :: Software Development :: Libraries :: Python Modules
Classifier: Topic :: Utilities
Classifier: Programming Language :: C++
Project-URL: Homepage, https://github.com/iwishiwasaneagle/libjdrones
Project-URL: Bug tracker, https://github.com/iwishiwasaneagle/libjdrones/issues
Project-URL: Discussions, https://github.comiwishiwasaneagle/libjdrones/discussions
Requires-Python: >=3.10
Provides-Extra: test
Requires-Dist: pytest; extra == "test"
Requires-Dist: numpy<2; extra == "test"
